setup.py
summoner.py
summoner.egg-info/PKG-INFO
summoner.egg-info/SOURCES.txt
summoner.egg-info/dependency_links.txt
summoner.egg-info/requires.txt
summoner.egg-info/top_level.txt