Metadata-Version: 1.0
Name: summoner
Version: 0.0.3
Summary: Work with the Serials Solutions Summon API
Home-page: http://github.com/edsu/summoner
Author: Ed Summers
Author-email: ehs@pobox.com
License: UNKNOWN
Platform: UNKNOWN
